db2pojo/__init__.py
db2pojo/cli.py
db2pojo/model.py
db2pojo/mysql.py
db2pojo/pojo.py
db2pojo/util.py
db2pojo-0.1.2.dist-info/METADATA
db2pojo-0.1.2.dist-info/WHEEL
db2pojo-0.1.2.dist-info/entry_points.txt
db2pojo-0.1.2.dist-info/top_level.txt
db2pojo-0.1.2.dist-info/RECORD
